ezQpy.py
qasm_to_qcis/__init__.py
qasm_to_qcis/const.py
qasm_to_qcis/qasm.py
qasm_to_qcis/qasm_to_qcis.py
qcis_to_qasm/__init__.py
qcis_to_qasm/const.py
qcis_to_qasm/qcis.py
qcis_to_qasm/qcis_to_qasm.py
ezQpy-1.0.0.dist-info/METADATA
ezQpy-1.0.0.dist-info/WHEEL
ezQpy-1.0.0.dist-info/top_level.txt
ezQpy-1.0.0.dist-info/RECORD
