Metadata-Version: 2.1
Name: ezQpy
Version: 1.0.0
Summary: A SDK to use Quantum Computer @ quantumcomputer.ac.cn with QCIS.
Home-page: https://quantumcomputer.ac.cn
Author: Code42
Author-email: support@quantumcomputer.ac.cn
License: MIT
Platform: UNKNOWN
Classifier: License :: OSI Approved :: MIT License
Classifier: Programming Language :: Python
Classifier: Programming Language :: Python :: 3
Classifier: Programming Language :: Python :: 3.6
Classifier: Programming Language :: Python :: Implementation :: CPython
Classifier: Programming Language :: Python :: Implementation :: PyPy
Requires-Python: >=3.6.0
Requires-Dist: beautifulsoup4
Requires-Dist: numpy
Requires-Dist: requests
Requires-Dist: isqmap
Requires-Dist: sabreMapper
